access_key_extractor/__init__.py
access_key_extractor/extract_access_key.py
ml_access_key_extractor-0.1.0.dist-info/METADATA
ml_access_key_extractor-0.1.0.dist-info/WHEEL
ml_access_key_extractor-0.1.0.dist-info/top_level.txt
ml_access_key_extractor-0.1.0.dist-info/RECORD
