Metadata-Version: 2.1
Name: ml_access_key_extractor
Version: 0.1.0
Summary: Biblioteca para extrair chave de acesso na nota fiscal em PDF
Author: Guillerme Rezende Manhaes
License: MIT License
Keywords: nota_fiscal
Requires-Dist: pdfplumber
Requires-Dist: scikit-learn >=0.24.0
